tensorflow_datasets/__init__.py
tensorflow_datasets/conftest.py
tensorflow_datasets/import_public_api_test.py
tensorflow_datasets/import_test.py
tensorflow_datasets/public_api.py
tensorflow_datasets/version.py
tensorflow_datasets/version_stable.py
tensorflow_datasets/audio/__init__.py
tensorflow_datasets/audio/accentdb.py
tensorflow_datasets/audio/accentdb_test.py
tensorflow_datasets/audio/commonvoice.py
tensorflow_datasets/audio/commonvoice_test.py
tensorflow_datasets/audio/crema_d.py
tensorflow_datasets/audio/crema_d_test.py
tensorflow_datasets/audio/dementiabank.py
tensorflow_datasets/audio/dementiabank_test.py
tensorflow_datasets/audio/fuss.py
tensorflow_datasets/audio/fuss_test.py
tensorflow_datasets/audio/groove.py
tensorflow_datasets/audio/groove_test.py
tensorflow_datasets/audio/librispeech.py
tensorflow_datasets/audio/librispeech_test.py
tensorflow_datasets/audio/libritts.py
tensorflow_datasets/audio/libritts_test.py
tensorflow_datasets/audio/ljspeech.py
tensorflow_datasets/audio/ljspeech_test.py
tensorflow_datasets/audio/nsynth.py
tensorflow_datasets/audio/nsynth_test.py
tensorflow_datasets/audio/savee.py
tensorflow_datasets/audio/savee_test.py
tensorflow_datasets/audio/speech_commands.py
tensorflow_datasets/audio/speech_commands_test.py
tensorflow_datasets/audio/tedlium.py
tensorflow_datasets/audio/tedlium_test.py
tensorflow_datasets/audio/vctk.py
tensorflow_datasets/audio/vctk_test.py
tensorflow_datasets/audio/voxceleb.py
tensorflow_datasets/audio/voxceleb_test.py
tensorflow_datasets/audio/voxforge.py
tensorflow_datasets/audio/voxforge_test.py
tensorflow_datasets/audio/gtzan/__init__.py
tensorflow_datasets/audio/gtzan/dummy_data_generation.py
tensorflow_datasets/audio/gtzan/gtzan.py
tensorflow_datasets/audio/gtzan/gtzan_test.py
tensorflow_datasets/audio/gtzan_music_speech/__init__.py
tensorflow_datasets/audio/gtzan_music_speech/dummy_data_generation.py
tensorflow_datasets/audio/gtzan_music_speech/gtzan_music_speech.py
tfds_nightly_gradient-4.2.0.dev202102040822.dist-info/AUTHORS
tfds_nightly_gradient-4.2.0.dev202102040822.dist-info/LICENSE
tfds_nightly_gradient-4.2.0.dev202102040822.dist-info/METADATA
tfds_nightly_gradient-4.2.0.dev202102040822.dist-info/WHEEL
tfds_nightly_gradient-4.2.0.dev202102040822.dist-info/entry_points.txt
tfds_nightly_gradient-4.2.0.dev202102040822.dist-info/top_level.txt
tfds_nightly_gradient-4.2.0.dev202102040822.dist-info/RECORD
